Schemas/HelpEventCreated.py
Schemas/UserCreatedEvent.py
Schemas/__init__.py
PythonAvroSchemas-1.0.2.dist-info/LICENSE.txt
PythonAvroSchemas-1.0.2.dist-info/METADATA
PythonAvroSchemas-1.0.2.dist-info/WHEEL
PythonAvroSchemas-1.0.2.dist-info/top_level.txt
PythonAvroSchemas-1.0.2.dist-info/RECORD
